vhr_cloudmask/__init__.py
vhr_cloudmask/model/__init__.py
vhr_cloudmask/model/config/__init__.py
vhr_cloudmask/model/config/cloudmask_config.py
vhr_cloudmask/model/pipelines/__init__.py
vhr_cloudmask/model/pipelines/cloudmask_cnn_pipeline.py
vhr_cloudmask/model/templates/__init__.py
vhr_cloudmask/model/templates/cloudmask_default.yaml
vhr_cloudmask/view/__init__.py
vhr_cloudmask/view/cloudmask_cnn_pipeline_cli.py
vhr_cloudmask/view/cloudmask_rf_pipeline_cli.py
vhr_cloudmask-1.3.2.dist-info/LICENSE
vhr_cloudmask-1.3.2.dist-info/METADATA
vhr_cloudmask-1.3.2.dist-info/WHEEL
vhr_cloudmask-1.3.2.dist-info/entry_points.txt
vhr_cloudmask-1.3.2.dist-info/top_level.txt
vhr_cloudmask-1.3.2.dist-info/zip-safe
vhr_cloudmask-1.3.2.dist-info/RECORD
