Metadata-Version: 2.1
Name: vhr-cloudmask
Version: 1.3.2
Summary: Deep learning pipeline to cloud mask VHR imagery
Home-page: https://github.com/nasa-nccs-hpda/vhr-cloudmask
Author: jordancaraballo
Author-email: jordan.a.caraballo-vega@nasa.gov
License: BSD 3-Clause License
Project-URL: Documentation, https://github.com/nasa-nccs-hpda/vhr-cloudmask
Project-URL: Source, https://github.com/nasa-nccs-hpda/vhr-cloudmask
Project-URL: Issues, https://github.com/nasa-nccs-hpda/vhr-cloudmask/issues
Keywords: cloudmask,rioxarray,rasterio
Classifier: Development Status :: 4 - Beta
Classifier: Intended Audience :: Developers
Classifier: Intended Audience :: Science/Research
Classifier: Topic :: Software Development :: Libraries :: Python Modules
Classifier: License :: OSI Approved :: MIT License
Classifier: Programming Language :: Python :: 3 :: Only
Requires-Python: >=3.7
License-File: LICENSE
Requires-Dist: geopandas
Requires-Dist: rioxarray
Requires-Dist: xarray
Requires-Dist: rasterio
Requires-Dist: pandas
Requires-Dist: numpy
Requires-Dist: tqdm
Requires-Dist: localtileserver
Requires-Dist: omegaconf
Requires-Dist: tensorflow
Requires-Dist: tensorflow-caney
Requires-Dist: datasets
Requires-Dist: tiler
Requires-Dist: huggingface-hub
Provides-Extra: all
Requires-Dist: pdoc==8.0.1; extra == "all"
Requires-Dist: tensorflow-caney; extra == "all"
Requires-Dist: datasets; extra == "all"
Requires-Dist: tiler; extra == "all"
Requires-Dist: huggingface-hub; extra == "all"
Requires-Dist: pytest; extra == "all"
Requires-Dist: coverage[toml]; extra == "all"
Requires-Dist: black; extra == "all"
Provides-Extra: docs
Requires-Dist: pdoc==8.0.1; extra == "docs"
Requires-Dist: tensorflow-caney; extra == "docs"
Requires-Dist: datasets; extra == "docs"
Requires-Dist: tiler; extra == "docs"
Requires-Dist: huggingface-hub; extra == "docs"
Provides-Extra: test
Requires-Dist: pytest; extra == "test"
Requires-Dist: coverage[toml]; extra == "test"
Requires-Dist: black; extra == "test"
